docker/__init__.py
docker/client.py
docker/containers.py
docker/exec.py
docker/images.py
docker/networks.py
docker/session.py
docker/system.py
docker/volumes.py
docker_sdk-1.0.4.dist-info/LICENSE
docker_sdk-1.0.4.dist-info/METADATA
docker_sdk-1.0.4.dist-info/WHEEL
docker_sdk-1.0.4.dist-info/top_level.txt
docker_sdk-1.0.4.dist-info/RECORD
