Metadata-Version: 2.1
Name: docker-sdk
Version: 1.0.4
Summary: The docker python client supports asynchronous parallel access to containers.
Home-page: https://github.com/FreeTwilight/docker.git
Author: FreeTwilight
Author-email: zunpengyang@gmail.com
License: Apache License 2.0
Classifier: Programming Language :: Python :: 3
Classifier: License :: OSI Approved :: Apache Software License
Classifier: Operating System :: OS Independent
Requires-Python: >=3.6
License-File: LICENSE
Requires-Dist: aiohttp ==3.10.0
Requires-Dist: tqdm ==4.66.2
